literotica_dl/__init__.py
literotica_dl/__main__.py
literotica_dl/classes/Author.py
literotica_dl/classes/Story.py
literotica_dl/classes/__init__.py
literotica_dl-0.0.3.dist-info/entry_points.txt
literotica_dl-0.0.3.dist-info/WHEEL
literotica_dl-0.0.3.dist-info/METADATA
literotica_dl-0.0.3.dist-info/RECORD
